[{"AnimationName":"BasketballAction_0","ShootPositionX":0.275,"ShootPositionY":0.3,"ShootPositionZ":0.0},{"AnimationName":"BasketballAction_1","ShootPositionX":0.103,"ShootPositionY":0.087,"ShootPositionZ":0.07},{"AnimationName":"BasketballAction_100","ShootPositionX":0.177,"ShootPositionY":0.2,"ShootPositionZ":0.07},{"AnimationName":"BasketballAction_101","ShootPositionX":0.32,"ShootPositionY":0.5,"ShootPositionZ":0.0},{"AnimationName":"BasketballAction_102","ShootPositionX":0.5,"ShootPositionY":0.4,"ShootPositionZ":0.0},{"AnimationName":"BasketballAction_2","ShootPositionX":0.425,"ShootPositionY":0.65,"ShootPositionZ":0.0},{"AnimationName":"BasketballAction_3","ShootPositionX":0.4,"ShootPositionY":0.4,"ShootPositionZ":0.0},{"AnimationName":"BasketballAction_4","ShootPositionX":0.0,"ShootPositionY":0.5,"ShootPositionZ":0.0}]