[
    {
        "name": "BallTouchWall"
    },
    {
        "name": "DashSmoke"
    },
    {
        "name": "DC_Soul"
    },
    {
        "name": "DoubleClick"
    },
    {
        "name": "DunkFX"
    },
    {
        "name": "FallDownFX"
    },
    {
        "name": "FX_SelectDown"
    },
    {
        "name": "JumpDownFX"
    },
    {
        "name": "MoveTo"
    },
    {
        "name": "PassA"
    },
    {
        "name": "PassB"
    },
    {
        "name": "PassiveFX"
    },
    {
        "name": "PassMe"
    },
    {
        "name": "PlayerInfo"
    },
    {
        "name": "RangeOfAction"
    },
    {
        "name": "SelectA"
    },
    {
        "name": "SelectAni"
    },
    {
        "name": "SelectB"
    },
    {
        "name": "SelectMe"
    },
    {
        "name": "Shadow01"
    },
    {
        "name": "ShakeFX_0"
    },
    {
        "name": "ShotFX"
    },
    {
        "name": "ShowWord_Block"
    },
    {
        "name": "ShowWord_Dunk"
    },
    {
        "name": "ShowWord_NiceShot"
    },
    {
        "name": "ShowWord_Punch"
    },
    {
        "name": "ShowWord_Steal"
    },
    {
        "name": "ShowWord_Assist"
    },
    {
        "name": "SkillArea_Arrow"
    },
    {
        "name": "SkillArea_Circle"
    },
    {
        "name": "TeamFull"
    },
    {
        "name": "TeamJoin"
    },
    {
        "name": "TeamQuit"
    },
    {
        "name": "ThreeLineEffect"
    },
    {
        "name": "ThrowInLineEffect"
    },
    {
        "name": "UI_FX_A_21"
    },
    {
        "name": "UIEquipSkill"
    },
    {
        "name": "UnlockEffect"
    },
    {
        "name": "UseSkillEffect_40"
    },
    {
        "name": "UseSkillEffect_60"
    },
    {
        "name": "UseSkillEffect_70"
    },
    {
        "name": "UseSkillEffect_150"
    },
    {
        "name": "UseSkillEffect_180"
    },
    {
        "name": "UseSkillEffect_210"
    }
]