[{"FileName":"0.","PosAy1":[{"x":11.0,"z":0.0,"Speedup":false},{"x":0.0,"z":0.0,"Speedup":false},{"x":0.0,"z":0.0,"Speedup":false}],"PosAy2":[{"x":0.0,"z":0.0,"Speedup":false},{"x":0.0,"z":0.0,"Speedup":false},{"x":0.0,"z":0.0,"Speedup":false}],"PosAy3":[{"x":0.0,"z":0.0,"Speedup":false},{"x":0.0,"z":0.0,"Speedup":false},{"x":0.0,"z":22.0,"Speedup":false}]},{"FileName":"1.","PosAy1":[{"x":330.0,"z":0.0,"Speedup":false},{"x":0.0,"z":0.0,"Speedup":false}],"PosAy2":[{"x":0.0,"z":0.0,"Speedup":false},{"x":0.0,"z":0.0,"Speedup":false}],"PosAy3":[{"x":0.0,"z":0.0,"Speedup":false},{"x":0.0,"z":440.0,"Speedup":false}]},{"FileName":"2.","PosAy1":[{"x":50.0,"z":0.0,"Speedup":false},{"x":0.0,"z":0.0,"Speedup":false},{"x":0.0,"z":0.0,"Speedup":false}],"PosAy2":[{"x":0.0,"z":0.0,"Speedup":false},{"x":0.0,"z":0.0,"Speedup":false},{"x":0.0,"z":0.0,"Speedup":false}],"PosAy3":[{"x":0.0,"z":0.0,"Speedup":false},{"x":0.0,"z":0.0,"Speedup":false},{"x":0.0,"z":60.0,"Speedup":false}]},{"FileName":"3.","PosAy1":[{"x":250.0,"z":0.0,"Speedup":false},{"x":0.0,"z":0.0,"Speedup":false}],"PosAy2":[{"x":0.0,"z":0.0,"Speedup":false},{"x":0.0,"z":0.0,"Speedup":false}],"PosAy3":[{"x":0.0,"z":0.0,"Speedup":false},{"x":0.0,"z":350.0,"Speedup":false}]},{"FileName":"4.","PosAy1":[{"x":10000.0,"z":0.0,"Speedup":false}],"PosAy2":[{"x":0.0,"z":0.0,"Speedup":false}],"PosAy3":[{"x":0.0,"z":800.0,"Speedup":false}]}]