[
    {
        "teamname1tw": "場邊",
        "teamname2tw": "神準",
        "teamname3tw": "王",
        "teamname1cn": "场边",
        "teamname2cn": "神准",
        "teamname3cn": "王",
        "teamname1en": "Zoo",
        "teamname2en": "Big",
        "teamname3en": "Carl"
    },
    {
        "teamname1tw": "三分線",
        "teamname2tw": "妙傳",
        "teamname3tw": "老大",
        "teamname1cn": "三分线",
        "teamname2cn": "妙传",
        "teamname3cn": "老大",
        "teamname1en": "India",
        "teamname2en": "Boiling",
        "teamname3en": "Jake"
    },
    {
        "teamname1tw": "中線",
        "teamname2tw": "三冠",
        "teamname3tw": "硬漢",
        "teamname1cn": "中线",
        "teamname2cn": "三冠",
        "teamname3cn": "硬汉",
        "teamname1en": "Bathroom",
        "teamname2en": "Chilly",
        "teamname3en": "Mort"
    },
    {
        "teamname1tw": "四分線",
        "teamname2tw": "手滑",
        "teamname3tw": "橘子",
        "teamname1cn": "四分线",
        "teamname2cn": "手滑",
        "teamname3cn": "橘子",
        "teamname1en": "Taipei",
        "teamname2en": "Cold",
        "teamname3en": "Paul"
    },
    {
        "teamname1tw": "內線",
        "teamname2tw": "放槍",
        "teamname3tw": "漢堡",
        "teamname1cn": "内线",
        "teamname2cn": "放枪",
        "teamname3cn": "汉堡",
        "teamname1en": "Theater",
        "teamname2en": "Cool",
        "teamname3en": "Ben"
    },
    {
        "teamname1tw": "總統府",
        "teamname2tw": "失誤",
        "teamname3tw": "劍神",
        "teamname1cn": "总统府",
        "teamname2cn": "失误",
        "teamname3cn": "剑神",
        "teamname1en": "Hell",
        "teamname2en": "Curly",
        "teamname3en": "Kit"
    },
    {
        "teamname1tw": "捷運站",
        "teamname2tw": "麵包",
        "teamname3tw": "射手",
        "teamname1cn": "捷运站",
        "teamname2cn": "面包",
        "teamname3cn": "射手",
        "teamname1en": "Heaven",
        "teamname2en": "Dirty",
        "teamname3en": "Tony"
    },
    {
        "teamname1tw": "賣噹勞",
        "teamname2tw": "打鐵",
        "teamname3tw": "師傅",
        "teamname1cn": "卖当劳",
        "teamname2cn": "打铁",
        "teamname3cn": "师傅",
        "teamname1en": "Hospital",
        "teamname2en": "Dry",
        "teamname3en": "Jeff"
    },
    {
        "teamname1tw": "肯的雞",
        "teamname2tw": "硬幹",
        "teamname3tw": "姆斯",
        "teamname1cn": "肯的​​鸡",
        "teamname2cn": "硬干",
        "teamname3cn": "姆斯",
        "teamname1en": "Kitchen",
        "teamname2en": "Flaky",
        "teamname3en": "Luke"
    },
    {
        "teamname1tw": "宇宙",
        "teamname2tw": "飄",
        "teamname3tw": "國王",
        "teamname1cn": "宇宙",
        "teamname2cn": "飘",
        "teamname3cn": "国王",
        "teamname1en": "L.A.",
        "teamname2en": "Soft",
        "teamname3en": "Dud"
    },
    {
        "teamname1tw": "路邊",
        "teamname2tw": "打醬油",
        "teamname3tw": "遊俠",
        "teamname1cn": "路边",
        "teamname2cn": "打酱油",
        "teamname3cn": "游侠",
        "teamname1en": "Island",
        "teamname2en": "Juicy",
        "teamname3en": "Rob"
    },
    {
        "teamname1tw": "公車",
        "teamname2tw": "熱情",
        "teamname3tw": "刺客",
        "teamname1cn": "公车",
        "teamname2cn": "热情",
        "teamname3cn": "刺客",
        "teamname1en": "Hawaii",
        "teamname2en": "Ripe",
        "teamname3en": "Jack"
    },
    {
        "teamname1tw": "臉書",
        "teamname2tw": "自我",
        "teamname3tw": "魯蛇",
        "teamname1cn": "脸书",
        "teamname2cn": "自我",
        "teamname3cn": "鲁蛇",
        "teamname1en": "School",
        "teamname2en": "Fresh",
        "teamname3en": "Viv"
    },
    {
        "teamname1tw": "菜市場",
        "teamname2tw": "奔放",
        "teamname3tw": "雷射",
        "teamname1cn": "菜市场",
        "teamname2cn": "奔放",
        "teamname3cn": "雷射",
        "teamname1en": "Boat",
        "teamname2en": "Bitter",
        "teamname3en": "Vic"
    },
    {
        "teamname1tw": "飛行船",
        "teamname2tw": "自閉",
        "teamname3tw": "小弟",
        "teamname1cn": "飞行船",
        "teamname2cn": "自闭",
        "teamname3cn": "小弟",
        "teamname1en": "America",
        "teamname2en": "Sour",
        "teamname3en": "Bob"
    },
    {
        "teamname1tw": "辦公室",
        "teamname2tw": "跌倒",
        "teamname3tw": "勇者",
        "teamname1cn": "办公室",
        "teamname2cn": "跌倒",
        "teamname3cn": "勇者",
        "teamname1en": "Asia",
        "teamname2en": "Spicy",
        "teamname3en": "Glen"
    },
    {
        "teamname1tw": "旅行社",
        "teamname2tw": "腳滑",
        "teamname3tw": "鐵匠",
        "teamname1cn": "旅行社",
        "teamname2cn": "脚滑",
        "teamname3cn": "铁匠",
        "teamname1en": "Grill",
        "teamname2en": "Ice",
        "teamname3en": "Rod"
    },
    {
        "teamname1tw": "廟口",
        "teamname2tw": "低頭",
        "teamname3tw": "怪物",
        "teamname1cn": "庙口",
        "teamname2cn": "低头",
        "teamname3cn": "怪物",
        "teamname1en": "Bus",
        "teamname2en": "Hot",
        "teamname3en": "Bud"
    },
    {
        "teamname1tw": "村莊",
        "teamname2tw": "射籃",
        "teamname3tw": "鐵人",
        "teamname1cn": "村庄",
        "teamname2cn": "射篮",
        "teamname3cn": "铁人",
        "teamname1en": "Italy",
        "teamname2en": "Shory",
        "teamname3en": "Dale"
    },
    {
        "teamname1tw": "旅館",
        "teamname2tw": "打電話",
        "teamname3tw": "醫生",
        "teamname1cn": "旅馆",
        "teamname2cn": "打电话",
        "teamname3cn": "医生",
        "teamname1en": "America",
        "teamname2en": "Slow",
        "teamname3en": "Earl"
    },
    {
        "teamname1tw": "球場",
        "teamname2tw": "閃避",
        "teamname3tw": "律師",
        "teamname1cn": "球场",
        "teamname2cn": "闪避",
        "teamname3cn": "律师",
        "teamname1en": "Macao",
        "teamname2en": "Swift",
        "teamname3en": "Karl"
    },
    {
        "teamname1tw": "罰球線",
        "teamname2tw": "低調",
        "teamname3tw": "阿伯",
        "teamname1cn": "罚球线",
        "teamname2cn": "低调",
        "teamname3cn": "阿伯",
        "teamname1en": "Well",
        "teamname2en": "Old",
        "teamname3en": "Amy"
    },
    {
        "teamname1tw": "外交部",
        "teamname2tw": "高調",
        "teamname3tw": "阿公",
        "teamname1cn": "外交部",
        "teamname2cn": "高调",
        "teamname3cn": "阿公",
        "teamname1en": "Africa",
        "teamname2en": "Late",
        "teamname3en": "Dora"
    },
    {
        "teamname1tw": "彩券行",
        "teamname2tw": "追擊",
        "teamname3tw": "肥宅",
        "teamname1cn": "彩券行",
        "teamname2cn": "追击",
        "teamname3cn": "肥宅",
        "teamname1en": "Japan",
        "teamname2en": "Early",
        "teamname3en": "Eva"
    },
    {
        "teamname1tw": "校園",
        "teamname2tw": "絕殺",
        "teamname3tw": "劍仙",
        "teamname1cn": "校园",
        "teamname2cn": "绝杀",
        "teamname3cn": "剑仙",
        "teamname1en": "Opera",
        "teamname2en": "Fast",
        "teamname3en": "Viv"
    },
    {
        "teamname1tw": "醫院",
        "teamname2tw": "瘋狂",
        "teamname3tw": "熊貓",
        "teamname1cn": "医院",
        "teamname2cn": "疯狂",
        "teamname3cn": "熊猫",
        "teamname1en": "Ward",
        "teamname2en": "Fat",
        "teamname3en": "Nell"
    },
    {
        "teamname1tw": "峽谷",
        "teamname2tw": "摸魚",
        "teamname3tw": "海賊",
        "teamname1cn": "峡谷",
        "teamname2cn": "摸鱼",
        "teamname3cn": "海贼",
        "teamname1en": "Boston",
        "teamname2en": "Little",
        "teamname3en": "Ida"
    },
    {
        "teamname1tw": "火車",
        "teamname2tw": "切入",
        "teamname3tw": "球員",
        "teamname1cn": "蜀山",
        "teamname2cn": "切入",
        "teamname3cn": "球员",
        "teamname1en": "Greece",
        "teamname2en": "Large",
        "teamname3en": "Pat"
    },
    {
        "teamname1tw": "火山",
        "teamname2tw": "勾射",
        "teamname3tw": "海盜",
        "teamname1cn": "火山",
        "teamname2cn": "勾射",
        "teamname3cn": "海盗",
        "teamname1en": "Office",
        "teamname2en": "Hollow",
        "teamname3en": "Judy"
    },
    {
        "teamname1tw": "樓梯間",
        "teamname2tw": "多餘的",
        "teamname3tw": "王者",
        "teamname1cn": "楼梯间",
        "teamname2cn": "多余的",
        "teamname3cn": "王者",
        "teamname1en": "Theater",
        "teamname2en": "Flat",
        "teamname3en": "Anne"
    },
    {
        "teamname1tw": "富士山",
        "teamname2tw": "神奇的",
        "teamname3tw": "冠Ｃ",
        "teamname1cn": "富士山",
        "teamname2cn": "神奇的",
        "teamname3cn": "冠Ｃ",
        "teamname1en": "Ground",
        "teamname2en": "Steep",
        "teamname3en": "Ruby"
    },
    {
        "teamname1tw": "火車上",
        "teamname2tw": "慵懶",
        "teamname3tw": "工人",
        "teamname1cn": "火车上",
        "teamname2cn": "慵懒",
        "teamname3cn": "工人",
        "teamname1en": "Ground",
        "teamname2en": "Wide",
        "teamname3en": "Rita"
    },
    {
        "teamname1tw": "古井旁",
        "teamname2tw": "搞笑",
        "teamname3tw": "路人",
        "teamname1cn": "古井旁",
        "teamname2cn": "搞笑",
        "teamname3cn": "路人",
        "teamname1en": "Ocean",
        "teamname2en": "Flat",
        "teamname3en": "Viv"
    },
    {
        "teamname1tw": "摩鐵",
        "teamname2tw": "灑粉",
        "teamname3tw": "歌手",
        "teamname1cn": "摩铁",
        "teamname2cn": "洒粉",
        "teamname3cn": "歌手",
        "teamname1en": "Beijing",
        "teamname2en": "Short",
        "teamname3en": "Avis"
    },
    {
        "teamname1tw": "廚房",
        "teamname2tw": "邪惡",
        "teamname3tw": "藝人",
        "teamname1cn": "厨房",
        "teamname2cn": "邪恶",
        "teamname3cn": "艺人",
        "teamname1en": "NewYork",
        "teamname2en": "Small",
        "teamname3en": "Sal"
    },
    {
        "teamname1tw": "廁所",
        "teamname2tw": "迴轉",
        "teamname3tw": "老闆",
        "teamname1cn": "厕所",
        "teamname2cn": "回转",
        "teamname3cn": "老板",
        "teamname1en": "Canada",
        "teamname2en": "Puny",
        "teamname3en": "Ella"
    },
    {
        "teamname1tw": "超商",
        "teamname2tw": "包裝",
        "teamname3tw": "騎士",
        "teamname1cn": "超商",
        "teamname2cn": "包装",
        "teamname3cn": "骑士",
        "teamname1en": "Market",
        "teamname2en": "Great",
        "teamname3en": "Jan"
    },
    {
        "teamname1tw": "立法院",
        "teamname2tw": "擦玻璃",
        "teamname3tw": "士兵",
        "teamname1cn": "立法院",
        "teamname2cn": "擦玻璃",
        "teamname3cn": "士兵",
        "teamname1en": "Boston",
        "teamname2en": "Shrill",
        "teamname3en": "Flo"
    },
    {
        "teamname1tw": "修車廠",
        "teamname2tw": "健身",
        "teamname3tw": "劍士",
        "teamname1cn": "修车厂",
        "teamname2cn": "健身",
        "teamname3cn": "剑士",
        "teamname1en": "Asia",
        "teamname2en": "Lax",
        "teamname3en": "Abel"
    },
    {
        "teamname1tw": "地獄",
        "teamname2tw": "神秘",
        "teamname3tw": "胖子",
        "teamname1cn": "地狱",
        "teamname2cn": "神秘",
        "teamname3cn": "胖子",
        "teamname1en": "Africa",
        "teamname2en": "Curly",
        "teamname3en": "Abe"
    },
    {
        "teamname1tw": "天堂",
        "teamname2tw": "詭譎",
        "teamname3tw": "大帝",
        "teamname1cn": "天堂",
        "teamname2cn": "诡谲",
        "teamname3cn": "大帝",
        "teamname1en": "Hotel",
        "teamname2en": "Spicy",
        "teamname3en": "Andy"
    },
    {
        "teamname1tw": "軍隊",
        "teamname2tw": "陰險",
        "teamname3tw": "小偷",
        "teamname1cn": "奈何桥",
        "teamname2cn": "阴险",
        "teamname3cn": "小偷",
        "teamname1en": "Grave",
        "teamname2en": "Broken",
        "teamname3en": "Bert"
    },
    {
        "teamname1tw": "地下室",
        "teamname2tw": "霸氣",
        "teamname3tw": "男孩",
        "teamname1cn": "地下室",
        "teamname2cn": "霸气",
        "teamname3cn": "男孩",
        "teamname1en": "India",
        "teamname2en": "Mute",
        "teamname3en": "Bill"
    },
    {
        "teamname1tw": "報社",
        "teamname2tw": "可愛",
        "teamname3tw": "女孩",
        "teamname1cn": "报社",
        "teamname2cn": "可爱",
        "teamname3cn": "女孩",
        "teamname1en": "Greece",
        "teamname2en": "Noisy",
        "teamname3en": "Brad"
    },
    {
        "teamname1tw": "電影院",
        "teamname2tw": "逆襲",
        "teamname3tw": "雞",
        "teamname1cn": "电影院",
        "teamname2cn": "逆袭",
        "teamname3cn": "鸡",
        "teamname1en": "Miami",
        "teamname2en": "Quiet",
        "teamname3en": "Burt"
    },
    {
        "teamname1tw": "教室裡",
        "teamname2tw": "耍笨的",
        "teamname3tw": "牛",
        "teamname1cn": "教室里",
        "teamname2cn": "耍笨的",
        "teamname3cn": "牛",
        "teamname1en": "Prison",
        "teamname2en": "Low",
        "teamname3en": "Dale"
    },
    {
        "teamname1tw": "咖啡廳",
        "teamname2tw": "戀愛中",
        "teamname3tw": "老虎",
        "teamname1cn": "咖啡厅",
        "teamname2cn": "恋爱中",
        "teamname3cn": "老虎",
        "teamname1en": "Opera",
        "teamname2en": "High",
        "teamname3en": "Dan"
    },
    {
        "teamname1tw": "綠洲",
        "teamname2tw": "陽光",
        "teamname3tw": "熊",
        "teamname1cn": "绿洲",
        "teamname2cn": "阳光",
        "teamname3cn": "熊",
        "teamname1en": "Office",
        "teamname2en": "Faint",
        "teamname3en": "Eric"
    },
    {
        "teamname1tw": "必剩嗑",
        "teamname2tw": "憂鬱",
        "teamname3tw": "鮭魚",
        "teamname1cn": "必剩嗑",
        "teamname2cn": "忧郁",
        "teamname3cn": "鲑鱼",
        "teamname1en": "Airport",
        "teamname2en": "Harsh",
        "teamname3en": "Eli"
    },
    {
        "teamname1tw": "打美樂",
        "teamname2tw": "買犯",
        "teamname3tw": "玫瑰",
        "teamname1cn": "打美乐",
        "teamname2cn": "买犯",
        "teamname3cn": "玫瑰",
        "teamname1en": "Ocean",
        "teamname2en": "Warm",
        "teamname3en": "Carl"
    },
    {
        "teamname1tw": "熱音社",
        "teamname2tw": "自盡",
        "teamname3tw": "雛菊",
        "teamname1cn": "热音社",
        "teamname2cn": "自尽",
        "teamname3cn": "雏菊",
        "teamname1en": "Osaka",
        "teamname2en": "Angry",
        "teamname3en": "Jake"
    },
    {
        "teamname1tw": "籃球社",
        "teamname2tw": "罰球",
        "teamname3tw": "章魚",
        "teamname1cn": "篮球社",
        "teamname2cn": "罚球",
        "teamname3cn": "章鱼",
        "teamname1en": "Oasis",
        "teamname2en": "Awful",
        "teamname3en": "Mort"
    },
    {
        "teamname1tw": "校隊",
        "teamname2tw": "灌籃",
        "teamname3tw": "透抽",
        "teamname1cn": "校队",
        "teamname2cn": "灌篮",
        "teamname3cn": "透抽",
        "teamname1en": "Hospital",
        "teamname2en": "Bad",
        "teamname3en": "Paul"
    },
    {
        "teamname1tw": "地下城",
        "teamname2tw": "發球",
        "teamname3tw": "蛤蠣",
        "teamname1cn": "地下城",
        "teamname2cn": "发球",
        "teamname3cn": "蛤蛎",
        "teamname1en": "School",
        "teamname2en": "Black",
        "teamname3en": "Ben"
    },
    {
        "teamname1tw": "觀眾席",
        "teamname2tw": "騎射",
        "teamname3tw": "狗",
        "teamname1cn": "药王谷",
        "teamname2cn": "骑射",
        "teamname3cn": "狗",
        "teamname1en": "Train",
        "teamname2en": "Blue",
        "teamname3en": "Kit"
    },
    {
        "teamname1tw": "板凳",
        "teamname2tw": "聞腋",
        "teamname3tw": "歌王",
        "teamname1cn": "金陵",
        "teamname2cn": "闻腋",
        "teamname3cn": "歌王",
        "teamname1en": "Asia",
        "teamname2en": "Bored",
        "teamname3en": "Tony"
    },
    {
        "teamname1tw": "城堡裡",
        "teamname2tw": "競選的",
        "teamname3tw": "演員",
        "teamname1cn": "城堡里",
        "teamname2cn": "竞选的",
        "teamname3cn": "演员",
        "teamname1en": "Dream",
        "teamname2en": "Crazy",
        "teamname3en": "Jeff"
    },
    {
        "teamname1tw": "墳墓",
        "teamname2tw": "孤獨的",
        "teamname3tw": "教師",
        "teamname1cn": "坟墓",
        "teamname2cn": "孤独的",
        "teamname3cn": "教师",
        "teamname1en": "Castle",
        "teamname2en": "Flip",
        "teamname3en": "Luke"
    },
    {
        "teamname1tw": "墓園",
        "teamname2tw": "大聲的",
        "teamname3tw": "黑人",
        "teamname1cn": "墓园",
        "teamname2cn": "大声的",
        "teamname3cn": "黑人",
        "teamname1en": "NewYork",
        "teamname2en": "Cruel",
        "teamname3en": "Dud"
    },
    {
        "teamname1tw": "機場",
        "teamname2tw": "性感的",
        "teamname3tw": "瞎子",
        "teamname1cn": "海边",
        "teamname2cn": "性感的",
        "teamname3cn": "瞎子",
        "teamname1en": "Air",
        "teamname2en": "Dizzy",
        "teamname3en": "Rob"
    },
    {
        "teamname1tw": "太平洋",
        "teamname2tw": "無敵的",
        "teamname3tw": "馬",
        "teamname1cn": "太平洋",
        "teamname2cn": "无敌的",
        "teamname3cn": "马",
        "teamname1en": "Taipei",
        "teamname2en": "Dull",
        "teamname3en": "Jack"
    },
    {
        "teamname1tw": "亞洲",
        "teamname2tw": "青春",
        "teamname3tw": "豬",
        "teamname1cn": "亚洲",
        "teamname2cn": "青春",
        "teamname3cn": "猪",
        "teamname1en": "Zoo",
        "teamname2en": "Evil",
        "teamname3en": "Viv"
    },
    {
        "teamname1tw": "燒烤店",
        "teamname2tw": "火鍋",
        "teamname3tw": "兔子",
        "teamname1cn": "十里坡",
        "teamname2cn": "火锅",
        "teamname3cn": "兔子",
        "teamname1en": "Korea",
        "teamname2en": "Happy",
        "teamname3en": "Vic"
    },
    {
        "teamname1tw": "服飾店",
        "teamname2tw": "抄截",
        "teamname3tw": "教官",
        "teamname1cn": "服饰店",
        "teamname2cn": "抄截",
        "teamname3cn": "教官",
        "teamname1en": "Sky",
        "teamname2en": "Jolly",
        "teamname3en": "Bob"
    },
    {
        "teamname1tw": "監獄",
        "teamname2tw": "助攻",
        "teamname3tw": "飛官",
        "teamname1cn": "监狱",
        "teamname2cn": "助攻",
        "teamname3cn": "飞官",
        "teamname1en": "Heaven",
        "teamname2en": "Lovely",
        "teamname3en": "Glen"
    },
    {
        "teamname1tw": "銀行",
        "teamname2tw": "籃板",
        "teamname3tw": "教練",
        "teamname1cn": "银行",
        "teamname2cn": "篮板",
        "teamname3cn": "教练",
        "teamname1en": "Sea",
        "teamname2en": "Lucky",
        "teamname3en": "Rod"
    },
    {
        "teamname1tw": "金庫",
        "teamname2tw": "拋射",
        "teamname3tw": "法師",
        "teamname1cn": "金库",
        "teamname2cn": "抛射",
        "teamname3cn": "法师",
        "teamname1en": "Air",
        "teamname2en": "Nice",
        "teamname3en": "Bud"
    },
    {
        "teamname1tw": "台北",
        "teamname2tw": "禿頭",
        "teamname3tw": "歐肥",
        "teamname1cn": "台北",
        "teamname2cn": "秃头",
        "teamname3cn": "欧肥",
        "teamname1en": "Canyon",
        "teamname2en": "Calm",
        "teamname3en": "Dale"
    },
    {
        "teamname1tw": "東京",
        "teamname2tw": "地中海",
        "teamname3tw": "駕駛",
        "teamname1cn": "东京",
        "teamname2cn": "地中海",
        "teamname3cn": "驾驶",
        "teamname1en": "Dream",
        "teamname2en": "Brave",
        "teamname3en": "Earl"
    },
    {
        "teamname1tw": "大阪",
        "teamname2tw": "掉毛",
        "teamname3tw": "咖哩",
        "teamname1cn": "大阪",
        "teamname2cn": "掉毛",
        "teamname3cn": "咖喱",
        "teamname1en": "China",
        "teamname2en": "Fair",
        "teamname3en": "Karl"
    },
    {
        "teamname1tw": "劇院",
        "teamname2tw": "聰明的",
        "teamname3tw": "武士",
        "teamname1cn": "剧院",
        "teamname2cn": "聪明的",
        "teamname3cn": "武士",
        "teamname1en": "Brazil",
        "teamname2en": "Witty",
        "teamname3en": "Amy"
    },
    {
        "teamname1tw": "浴室",
        "teamname2tw": "健忘的",
        "teamname3tw": "船長",
        "teamname1cn": "浴室",
        "teamname2cn": "健忘的",
        "teamname3cn": "船长",
        "teamname1en": "Village",
        "teamname2en": "Gentle",
        "teamname3en": "Dora"
    },
    {
        "teamname1tw": "歌劇院",
        "teamname2tw": "打麻將",
        "teamname3tw": "保羅",
        "teamname1cn": "歌剧院",
        "teamname2cn": "打麻将",
        "teamname3cn": "保罗",
        "teamname1en": "Village",
        "teamname2en": "Good",
        "teamname3en": "Eva"
    },
    {
        "teamname1tw": "運動場",
        "teamname2tw": "中年",
        "teamname3tw": "神手",
        "teamname1cn": "运动场",
        "teamname2cn": "中年",
        "teamname3cn": "神手",
        "teamname1en": "Club",
        "teamname2en": "Zany",
        "teamname3en": "Viv"
    },
    {
        "teamname1tw": "大樹下",
        "teamname2tw": "神經質",
        "teamname3tw": "遜咖",
        "teamname1cn": "大树下",
        "teamname2cn": "神经质",
        "teamname3cn": "逊咖",
        "teamname1en": "Club",
        "teamname2en": "Fine",
        "teamname3en": "Nell"
    },
    {
        "teamname1tw": "東南亞",
        "teamname2tw": "優雅的",
        "teamname3tw": "將軍",
        "teamname1cn": "东南亚",
        "teamname2cn": "优雅的",
        "teamname3cn": "将军",
        "teamname1en": "Sky",
        "teamname2en": "Super",
        "teamname3en": "Ida"
    },
    {
        "teamname1tw": "軍營裡",
        "teamname2tw": "無雙的",
        "teamname3tw": "隊長",
        "teamname1cn": "军营里",
        "teamname2cn": "无双的",
        "teamname3cn": "队长",
        "teamname1en": "Kitchen",
        "teamname2en": "Tame",
        "teamname3en": "Pat"
    },
    {
        "teamname1tw": "動物園",
        "teamname2tw": "傳奇的",
        "teamname3tw": "超人",
        "teamname1cn": "动物园",
        "teamname2cn": "传奇的",
        "teamname3cn": "超人",
        "teamname1en": "Airport",
        "teamname2en": "Vast",
        "teamname3en": "Judy"
    },
    {
        "teamname1tw": "餐廳",
        "teamname2tw": "做作的",
        "teamname3tw": "學生",
        "teamname1cn": "餐厅",
        "teamname2cn": "做作的",
        "teamname3cn": "学生",
        "teamname1en": "Oasis",
        "teamname2en": "Wild",
        "teamname3en": "Anne"
    },
    {
        "teamname1tw": "補習班",
        "teamname2tw": "不凡的",
        "teamname3tw": "少爺",
        "teamname1cn": "补习班",
        "teamname2cn": "不凡的",
        "teamname3cn": "少爷",
        "teamname1en": "Canada",
        "teamname2en": "Odd",
        "teamname3en": "Ruby"
    },
    {
        "teamname1tw": "幼稚園",
        "teamname2tw": "煞氣a",
        "teamname3tw": "公主",
        "teamname1cn": "幼稚园",
        "teamname2cn": "煞气a",
        "teamname3cn": "公主",
        "teamname1en": "Italy",
        "teamname2en": "Better",
        "teamname3en": "Rita"
    },
    {
        "teamname1tw": "警局",
        "teamname2tw": "被遺忘",
        "teamname3tw": "王子",
        "teamname1cn": "警局",
        "teamname2cn": "被遗忘",
        "teamname3cn": "王子",
        "teamname1en": "Ward",
        "teamname2en": "Frail",
        "teamname3en": "Viv"
    },
    {
        "teamname1tw": "派出所",
        "teamname2tw": "碎念",
        "teamname3tw": "女王",
        "teamname1cn": "派出所",
        "teamname2cn": "碎念",
        "teamname3cn": "女王",
        "teamname1en": "Holes",
        "teamname2en": "Light",
        "teamname3en": "Avis"
    },
    {
        "teamname1tw": "病房",
        "teamname2tw": "挨罵",
        "teamname3tw": "驢子",
        "teamname1cn": "病房",
        "teamname2cn": "挨骂",
        "teamname3cn": "驴子",
        "teamname1en": "U.K",
        "teamname2en": "Long",
        "teamname3en": "Sal"
    },
    {
        "teamname1tw": "ＫＴＶ",
        "teamname2tw": "調皮",
        "teamname3tw": "屁孩",
        "teamname1cn": "湖边",
        "teamname2cn": "调皮",
        "teamname3cn": "屁孩",
        "teamname1en": "Paris",
        "teamname2en": "Ugly",
        "teamname3en": "Ella"
    },
    {
        "teamname1tw": "夢境中",
        "teamname2tw": "搗蛋",
        "teamname3tw": "艾倫",
        "teamname1cn": "梦境中",
        "teamname2cn": "捣蛋",
        "teamname3cn": "艾伦",
        "teamname1en": "Movie",
        "teamname2en": "Fancy",
        "teamname3en": "Jan"
    },
    {
        "teamname1tw": "中國",
        "teamname2tw": "意外的",
        "teamname3tw": "土狼",
        "teamname1cn": "中国",
        "teamname2cn": "意外的",
        "teamname3cn": "土狼",
        "teamname1en": "Hotel",
        "teamname2en": "Shy",
        "teamname3en": "Flo"
    },
    {
        "teamname1tw": "小巨蛋",
        "teamname2tw": "大方",
        "teamname3tw": "雷神",
        "teamname1cn": "木叶村",
        "teamname2cn": "大方",
        "teamname3cn": "雷神",
        "teamname1en": "Island",
        "teamname2en": "Real",
        "teamname3en": "Abel"
    },
    {
        "teamname1tw": "坑洞裡",
        "teamname2tw": "小氣",
        "teamname3tw": "傷患",
        "teamname1cn": "坑洞里",
        "teamname2cn": "小气",
        "teamname3cn": "伤患",
        "teamname1en": "Cafe",
        "teamname2en": "Rich",
        "teamname3en": "Abe"
    },
    {
        "teamname1tw": "白洞",
        "teamname2tw": "衝動",
        "teamname3tw": "戰神",
        "teamname1cn": "白洞",
        "teamname2cn": "冲动",
        "teamname3cn": "战神",
        "teamname1en": "Canyon",
        "teamname2en": "Frail",
        "teamname3en": "Andy"
    },
    {
        "teamname1tw": "黑洞",
        "teamname2tw": "激動",
        "teamname3tw": "小鬼",
        "teamname1cn": "黑洞",
        "teamname2cn": "激动",
        "teamname3cn": "小鬼",
        "teamname1en": "Osaka",
        "teamname2en": "Bloody",
        "teamname3en": "Bert"
    },
    {
        "teamname1tw": "古代",
        "teamname2tw": "扯",
        "teamname3tw": "浪人",
        "teamname1cn": "古代",
        "teamname2cn": "扯",
        "teamname3cn": "浪人",
        "teamname1en": "Beijing",
        "teamname2en": "Cute",
        "teamname3en": "Bill"
    },
    {
        "teamname1tw": "現代",
        "teamname2tw": "恐怖",
        "teamname3tw": "流氓",
        "teamname1cn": "现代",
        "teamname2cn": "恐怖",
        "teamname3cn": "流氓",
        "teamname1en": "Court",
        "teamname2en": "Drab",
        "teamname3en": "Brad"
    },
    {
        "teamname1tw": "實驗室",
        "teamname2tw": "迷人",
        "teamname3tw": "偵探",
        "teamname1cn": "海边",
        "teamname2cn": "迷人",
        "teamname3cn": "侦探",
        "teamname1en": "MRT",
        "teamname2en": "Dull",
        "teamname3en": "Burt"
    },
    {
        "teamname1tw": "樂園",
        "teamname2tw": "帥氣",
        "teamname3tw": "基德",
        "teamname1cn": "乐园",
        "teamname2cn": "帅气",
        "teamname3cn": "基德",
        "teamname1en": "China",
        "teamname2en": "Dark",
        "teamname3en": "Dale"
    },
    {
        "teamname1tw": "空中",
        "teamname2tw": "中二",
        "teamname3tw": "司機",
        "teamname1cn": "空中",
        "teamname2cn": "中二",
        "teamname3cn": "司机",
        "teamname1en": "Police",
        "teamname2en": "Clean",
        "teamname3en": "Dan"
    },
    {
        "teamname1tw": "禮品店",
        "teamname2tw": "夢幻",
        "teamname3tw": "官員",
        "teamname1cn": "水里",
        "teamname2cn": "梦幻",
        "teamname3cn": "官员",
        "teamname1en": "Arena",
        "teamname2en": "Clear",
        "teamname3en": "Eric"
    },
    {
        "teamname1tw": "陸地",
        "teamname2tw": "國寶",
        "teamname3tw": "總統",
        "teamname1cn": "陆地",
        "teamname2cn": "国宝",
        "teamname3cn": "总统",
        "teamname1en": "Paris",
        "teamname2en": "Wet",
        "teamname3en": "Eli"
    },
    {
        "teamname1tw": "室內",
        "teamname2tw": "華麗",
        "teamname3tw": "委員",
        "teamname1cn": "室内",
        "teamname2cn": "华丽",
        "teamname3cn": "委员",
        "teamname1en": "Grill",
        "teamname2en": "Solid",
        "teamname3en": "Pat"
    },
    {
        "teamname1tw": "室外",
        "teamname2tw": "神",
        "teamname3tw": "傻子",
        "teamname1cn": "室外",
        "teamname2cn": "神",
        "teamname3cn": "傻子",
        "teamname1en": "Holes",
        "teamname2en": "Tall",
        "teamname3en": "Judy"
    }
]